rebecca.todict-0.5-py2.7-nspkg.pth
rebecca/todict/renderers.py
rebecca/todict/__init__.py
rebecca.todict-0.5.dist-info/DESCRIPTION.rst
rebecca.todict-0.5.dist-info/METADATA
rebecca.todict-0.5.dist-info/namespace_packages.txt
rebecca.todict-0.5.dist-info/pydist.json
rebecca.todict-0.5.dist-info/RECORD
rebecca.todict-0.5.dist-info/top_level.txt
rebecca.todict-0.5.dist-info/WHEEL
