Metadata-Version: 2.0
Name: rebecca.todict
Version: 0.5
Summary: API and directive converting object to ``dict``.
Home-page: https://github.com/rebeccaframework/rebecca.todict
Author: Atsushi Odagiri
Author-email: aodagx@gmail.com
License: MIT
Platform: UNKNOWN
Classifier: Development Status :: 3 - Alpha
Classifier: Framework :: Pyramid
Classifier: License :: OSI Approved :: MIT License
Classifier: Programming Language :: Python
Classifier: Programming Language :: Python :: 2.7
Classifier: Programming Language :: Python :: 3
Classifier: Programming Language :: Python :: 3.3
Requires-Dist: pyramid
Provides-Extra: testing
Requires-Dist: pytest; extra == 'testing'
Requires-Dist: webtest; extra == 'testing'
